zq_tools/__init__.py
zq_tools/zq_bogger.py
zq_tools/zq_cycle.py
zq_tools/zq_decorator.py
zq_tools/zq_files.py
zq_tools/zq_logger.py
zq_tools/zq_serialize.py
zq_tools/zq_tracing.py
zq_tools/bogging/__init__.py
zq_tools/bogging/config.py
zq_tools/bogging/handlers.py
zq_tools-1.1.6.dist-info/METADATA
zq_tools-1.1.6.dist-info/WHEEL
zq_tools-1.1.6.dist-info/top_level.txt
zq_tools-1.1.6.dist-info/RECORD
