Metadata-Version: 2.1
Name: zq-tools
Version: 1.1.6
Summary: A collection of tools for zzqq2199
Author: zzqq2199
Author-email: zhouquanjs@qq.com
Classifier: Programming Language :: Python :: 3
Classifier: License :: OSI Approved :: MIT License
Classifier: Operating System :: OS Independent
Requires-Dist: colorlog>=6.6
Requires-Dist: colorful
Requires-Dist: bogging
